easyfc/__init__.py
easyfc/hello.py
easyfc/parse.py
easyfc/response.py
easyfc-0.0.11.dist-info/METADATA
easyfc-0.0.11.dist-info/WHEEL
easyfc-0.0.11.dist-info/top_level.txt
easyfc-0.0.11.dist-info/RECORD
