Metadata-Version: 2.1
Name: easyfc
Version: 0.0.11
Summary: 适用于FasS业务的获取参数列表以及返回错误信息库
Home-page: https://github.com/
Author: terryZ
Author-email: zhengcairui@foxmail.com
License: UNKNOWN
Platform: UNKNOWN
Classifier: Programming Language :: Python :: 3
Classifier: License :: OSI Approved :: MIT License
Classifier: Operating System :: OS Independent
Requires-Python: >=3.6
